rigbysdk/__init__.py
rigbysdk/client.py
rigbysdk/sdk.py
rigbysdk/routes/__init__.py
rigbysdk/routes/notifications.py
rigbysdk/routes/user.py
rigbysdk/routes/gdps/__init__.py
rigbysdk/routes/gdps/analytics.py
rigbysdk/routes/gdps/config.py
rigbysdk/routes/gdps/gauntlets.py
rigbysdk/routes/gdps/levels.py
rigbysdk/routes/gdps/mappacks.py
rigbysdk/routes/gdps/masonlab.py
rigbysdk/routes/gdps/music.py
rigbysdk/routes/gdps/player.py
rigbysdk/routes/gdps/players.py
rigbysdk/routes/gdps/public.py
rigbysdk/routes/gdps/quests.py
rigbysdk/routes/gdps/roles.py
rigbysdk/routes/gdps/server.py
rigbysdk-0.1.0.dist-info/METADATA
rigbysdk-0.1.0.dist-info/WHEEL
rigbysdk-0.1.0.dist-info/licenses/LICENSE
rigbysdk-0.1.0.dist-info/RECORD
