Metadata-Version: 2.4
Name: rigbysdk
Version: 0.1.0
Summary: Python SDK for the Rigby API (parity with the TypeScript SDK).
Project-URL: Homepage, https://rigby.host
Project-URL: Repository, https://github.com/rigbyhost
Author-email: Rigby <support@rigby.host>
License: GPL-3.0-only
License-File: LICENSE
Requires-Python: >=3.9
Requires-Dist: requests>=2.31.0
